tergite_autocalibration/__init__.py
tergite_autocalibration/config/__init__.py
tergite_autocalibration/config/base.py
tergite_autocalibration/config/device.py
tergite_autocalibration/config/env.py
tergite_autocalibration/config/globals.py
tergite_autocalibration/config/handler.py
tergite_autocalibration/config/legacy.py
tergite_autocalibration/config/node.py
tergite_autocalibration/config/package.py
tergite_autocalibration/config/run.py
tergite_autocalibration/config/samplespace.py
tergite_autocalibration/config/spi.py
tergite_autocalibration/config/templates/templates-readme.md
tergite_autocalibration/config/templates/.default/configuration.meta.toml
tergite_autocalibration/config/templates/.default/configs/cluster_config.json
tergite_autocalibration/config/templates/.default/configs/device_config.toml
tergite_autocalibration/config/templates/.default/configs/node_config.toml
tergite_autocalibration/config/templates/.default/configs/run_config.toml
tergite_autocalibration/config/templates/.default/configs/spi_config.toml
tergite_autocalibration/config/templates/.default/configs/user_samplespace.py
tergite_autocalibration/config/templates/.default/j2_templates/device_config.j2
tergite_autocalibration/config/templates/.default/j2_templates/run_config.j2
tergite_autocalibration/config/templates/.default/misc/mixer_correction.csv
tergite_autocalibration/config/templates/fc7_2qc/configs/cluster_config.json
tergite_autocalibration/config/templates/fc7_2qc/configs/device_config.toml
tergite_autocalibration/config/templates/fc7_2qc/configs/node_config.toml
tergite_autocalibration/config/templates/fc7_2qc/configs/run_config.toml
tergite_autocalibration/config/templates/fc7_2qc/configs/spi_config.toml
tergite_autocalibration/config/templates/fc7_2qc/configs/user_samplespace.py
tergite_autocalibration/config/templates/fc8a/configuration.meta.toml
tergite_autocalibration/config/templates/fc8a/configs/cluster_config.json
tergite_autocalibration-2025.9.0.dist-info/licenses/LICENSE.txt
tergite_autocalibration-2025.9.0.dist-info/METADATA
tergite_autocalibration-2025.9.0.dist-info/WHEEL
tergite_autocalibration-2025.9.0.dist-info/entry_points.txt
tergite_autocalibration-2025.9.0.dist-info/top_level.txt
tergite_autocalibration-2025.9.0.dist-info/RECORD
