Metadata-Version: 2.4
Name: tergite-autocalibration
Version: 2025.9.0
Summary: Commandline application to calibrate the WACQT quantum computers automatically
Author-email: Eleftherios Moschandreou <elemos@chalmers.se>, Liangyu Chen <liangyuc@chalmers.se>, Stefan Hill <stefanhi@chalmers.se>, Amr Osman <oarm@chalmers.se>, Tong Liu <liuto@chalmers.se>, Joel Sandås <sandas@chalmers.se>, Pontus Vikstål <pontus.vikstal@chalmersnextlabs.se>, Michele Faucci Giannelli <faucci@chalmers.se>, Axel Erik Andersson <axean@chalmers.se>
Maintainer-email: Chalmers Next Labs AB <contact@quantum.chalmersnextlabs.se>
Requires-Python: <3.13,>=3.12
License-File: LICENSE.txt
Requires-Dist: pyqt5-qt5==5.15.2; platform_system == "Linux"
Requires-Dist: pyqt5-qt5==5.15.2; platform_system == "Windows"
Requires-Dist: pyqt5-qt5<6.0.0,>=5.15.2; platform_system == "Darwin"
Requires-Dist: colorama==0.4.6
Requires-Dist: h5netcdf==1.4.0
Requires-Dist: h5py>=3.12.1
Requires-Dist: Jinja2==3.1.2
Requires-Dist: numpy>=2.0
Requires-Dist: qblox-instruments==0.14.2
Requires-Dist: qcodes==0.49.0
Requires-Dist: quantify-core==0.7.8
Requires-Dist: quantify-scheduler==0.21.2
Requires-Dist: redis==5.0.0
Requires-Dist: scikit-learn==1.5.2
Requires-Dist: toml==0.10.2
Requires-Dist: python-dotenv==1.0.1
Requires-Dist: requests>=2.32.3
Requires-Dist: typer>=0.12.5
Requires-Dist: jokeapi==1.0.5
Requires-Dist: optuna==4.0.0
Requires-Dist: netcdf4==1.7.1.post2
Requires-Dist: tomlkit>=0.13.2
Requires-Dist: rich>=14.0.0
Requires-Dist: click<8.2.0
Requires-Dist: matplotlib>=3.9.3
Requires-Dist: scipy>=1.14.1
Requires-Dist: pandas>=2.2.3
Requires-Dist: xarray>=2024.11.0
Requires-Dist: filelock>=3.16.1
Requires-Dist: pyqtgraph>=0.13.7
Requires-Dist: pyqt5>=5.15.11
Requires-Dist: pydantic==2.9.2
Requires-Dist: dash>=3.1.1
Requires-Dist: dash-renderjson>=0.0.1
Provides-Extra: dev
Requires-Dist: jupyter>=1.0.0; extra == "dev"
Requires-Dist: black>=24.10.0; extra == "dev"
Requires-Dist: isort>=5.12.0; extra == "dev"
Requires-Dist: pylint>=3.3.8; extra == "dev"
Provides-Extra: docs
Requires-Dist: mkdocs-material==9.6.14; extra == "docs"
Requires-Dist: mkdocstrings[python]~=0.29; extra == "docs"
Requires-Dist: mkdocs-gen-files==0.5.0; extra == "docs"
Requires-Dist: mkdocs-literate-nav==0.6.2; extra == "docs"
Requires-Dist: mkdocs-bibtex==4.2.10; extra == "docs"
Requires-Dist: mkdocs-jupyter==0.25.1; extra == "docs"
Provides-Extra: test
Requires-Dist: pytest>=8.3.3; extra == "test"
Requires-Dist: requests-mock>=1.11.0; extra == "test"
Requires-Dist: pytest-cov>=7.0.0; extra == "test"
Dynamic: license-file
